tabotools/__init__.py
tabotools/data_preprocessor.py
tabotools/data_processor.py
tabotools/data_visualizer.py
tabotools/exploratory_data_analyzer.py
tabotools/file_loader.py
tabotools-0.1.5.dist-info/LICENSE
tabotools-0.1.5.dist-info/METADATA
tabotools-0.1.5.dist-info/WHEEL
tabotools-0.1.5.dist-info/top_level.txt
tabotools-0.1.5.dist-info/RECORD
