Metadata-Version: 2.2
Name: tabotools
Version: 0.1.5
Summary: A data tools library for loading, preprocessing, exploratory analysis, and visualization.
Author-email: Maria <vpays.am@gmail.com>
License: MIT
Project-URL: Homepage, https://github.com/Mariiavs/tabotools
Project-URL: Repository, https://github.com/Mariiavs/tabotools
Project-URL: Issues, https://github.com/Mariiavs/tabotools/issues
Requires-Python: >=3.6
License-File: LICENSE
Requires-Dist: pandas>=1.2.4
Requires-Dist: matplotlib>=3.3.4
Requires-Dist: seaborn>=0.11.1
Requires-Dist: ipython>=7.25.0
